<?xml version="1.0" encoding="UTF-8"?>
<?xml-stylesheet type="text/xsl" href="ALPS.xsl"?>
<SIMULATION xmlns:xsi="http://www.w3.org/2001/XMLSchema-instance" xsi:noNamespaceSchemaLocation="http://xml.comp-phys.org/2002/10/ALPS.xsd">
  <PARAMETERS>
    <PARAMETER name="NUMBER_EIGENVALUES">2</PARAMETER>
    <PARAMETER name="local_S">0.5</PARAMETER>
    <PARAMETER name="J">1</PARAMETER>
    <PARAMETER name="L">8</PARAMETER>
    <PARAMETER name="LATTICE">chain lattice</PARAMETER>
    <PARAMETER name="SEED">1</PARAMETER>
    <PARAMETER name="T">1</PARAMETER>
    <PARAMETER name="MODEL">spin</PARAMETER>
    <PARAMETER name="LATTICE_LIBRARY">lattices.xml</PARAMETER>
    <PARAMETER name="h">0</PARAMETER>
    <PARAMETER name="SWEEPS">60000</PARAMETER>
    <PARAMETER name="THERMALIZATION">20000</PARAMETER>
  </PARAMETERS>
  <AVERAGES>
    <SCALAR_AVERAGE name="Energy">
      <COUNT>63223</COUNT>
      <MEAN method="simple">-1.63462</MEAN>
      <ERROR converged="yes" method="binning">0.0162</ERROR>
      <VARIANCE method="simple">5.17</VARIANCE>
      <AUTOCORR method="binning">1.11</AUTOCORR>
      <BINNED size="1"><COUNT>63223</COUNT><MEAN method="simple">-1.63462</MEAN><ERROR method="simple">0.00904</ERROR></BINNED>
      <BINNED size="2"><COUNT>31611</COUNT><MEAN method="simple">-1.63464</MEAN><ERROR method="simple">0.011</ERROR></BINNED>
      <BINNED size="4"><COUNT>15805</COUNT><MEAN method="simple">-1.63471</MEAN><ERROR method="simple">0.013</ERROR></BINNED>
      <BINNED size="8"><COUNT>7902</COUNT><MEAN method="simple">-1.63472</MEAN><ERROR method="simple">0.0145</ERROR></BINNED>
      <BINNED size="16"><COUNT>3951</COUNT><MEAN method="simple">-1.63472</MEAN><ERROR method="simple">0.0154</ERROR></BINNED>
      <BINNED size="32"><COUNT>1975</COUNT><MEAN method="simple">-1.63452</MEAN><ERROR method="simple">0.0159</ERROR></BINNED>
      <BINNED size="64"><COUNT>987</COUNT><MEAN method="simple">-1.63413</MEAN><ERROR method="simple">0.016</ERROR></BINNED>
      <BINNED size="128"><COUNT>493</COUNT><MEAN method="simple">-1.63383</MEAN><ERROR method="simple">0.016</ERROR></BINNED>
      <BINNED size="256"><COUNT>246</COUNT><MEAN method="simple">-1.63304</MEAN><ERROR method="simple">0.0162</ERROR></BINNED>
    </SCALAR_AVERAGE>
    <SCALAR_AVERAGE name="Energy Density">
      <COUNT>63223</COUNT>
      <MEAN method="simple">-0.204327</MEAN>
      <ERROR converged="yes" method="binning">0.00203</ERROR>
      <VARIANCE method="simple">0.0808</VARIANCE>
      <AUTOCORR method="binning">1.11</AUTOCORR>
      <BINNED size="1"><COUNT>63223</COUNT><MEAN method="simple">-0.204327</MEAN><ERROR method="simple">0.00113</ERROR></BINNED>
      <BINNED size="2"><COUNT>31611</COUNT><MEAN method="simple">-0.204331</MEAN><ERROR method="simple">0.00137</ERROR></BINNED>
      <BINNED size="4"><COUNT>15805</COUNT><MEAN method="simple">-0.204339</MEAN><ERROR method="simple">0.00162</ERROR></BINNED>
      <BINNED size="8"><COUNT>7902</COUNT><MEAN method="simple">-0.20434</MEAN><ERROR method="simple">0.00182</ERROR></BINNED>
      <BINNED size="16"><COUNT>3951</COUNT><MEAN method="simple">-0.20434</MEAN><ERROR method="simple">0.00192</ERROR></BINNED>
      <BINNED size="32"><COUNT>1975</COUNT><MEAN method="simple">-0.204315</MEAN><ERROR method="simple">0.00198</ERROR></BINNED>
      <BINNED size="64"><COUNT>987</COUNT><MEAN method="simple">-0.204266</MEAN><ERROR method="simple">0.002</ERROR></BINNED>
      <BINNED size="128"><COUNT>493</COUNT><MEAN method="simple">-0.204229</MEAN><ERROR method="simple">0.00199</ERROR></BINNED>
      <BINNED size="256"><COUNT>246</COUNT><MEAN method="simple">-0.20413</MEAN><ERROR method="simple">0.00203</ERROR></BINNED>
    </SCALAR_AVERAGE>
    <SCALAR_AVERAGE name="Kinetic Energy">
      <COUNT>63223</COUNT>
      <MEAN method="simple">-1.0925</MEAN>
      <ERROR converged="yes" method="binning">0.0112</ERROR>
      <VARIANCE method="simple">2.03</VARIANCE>
      <AUTOCORR method="binning">1.44</AUTOCORR>
      <BINNED size="1"><COUNT>63223</COUNT><MEAN method="simple">-1.09245</MEAN><ERROR method="simple">0.00566</ERROR></BINNED>
      <BINNED size="2"><COUNT>31611</COUNT><MEAN method="simple">-1.09247</MEAN><ERROR method="simple">0.00715</ERROR></BINNED>
      <BINNED size="4"><COUNT>15805</COUNT><MEAN method="simple">-1.0925</MEAN><ERROR method="simple">0.00868</ERROR></BINNED>
      <BINNED size="8"><COUNT>7902</COUNT><MEAN method="simple">-1.09248</MEAN><ERROR method="simple">0.00991</ERROR></BINNED>
      <BINNED size="16"><COUNT>3951</COUNT><MEAN method="simple">-1.09248</MEAN><ERROR method="simple">0.0106</ERROR></BINNED>
      <BINNED size="32"><COUNT>1975</COUNT><MEAN method="simple">-1.09234</MEAN><ERROR method="simple">0.0109</ERROR></BINNED>
      <BINNED size="64"><COUNT>987</COUNT><MEAN method="simple">-1.092</MEAN><ERROR method="simple">0.0111</ERROR></BINNED>
      <BINNED size="128"><COUNT>493</COUNT><MEAN method="simple">-1.09185</MEAN><ERROR method="simple">0.0109</ERROR></BINNED>
      <BINNED size="256"><COUNT>246</COUNT><MEAN method="simple">-1.0915</MEAN><ERROR method="simple">0.0112</ERROR></BINNED>
    </SCALAR_AVERAGE>
    <SCALAR_AVERAGE name="Kinetic Energy Density">
      <COUNT>63223</COUNT>
      <MEAN method="simple">-0.13656</MEAN>
      <ERROR converged="yes" method="binning">0.00139</ERROR>
      <VARIANCE method="simple">0.0317</VARIANCE>
      <AUTOCORR method="binning">1.44</AUTOCORR>
      <BINNED size="1"><COUNT>63223</COUNT><MEAN method="simple">-0.136556</MEAN><ERROR method="simple">0.000708</ERROR></BINNED>
      <BINNED size="2"><COUNT>31611</COUNT><MEAN method="simple">-0.136558</MEAN><ERROR method="simple">0.000894</ERROR></BINNED>
      <BINNED size="4"><COUNT>15805</COUNT><MEAN method="simple">-0.136563</MEAN><ERROR method="simple">0.00108</ERROR></BINNED>
      <BINNED size="8"><COUNT>7902</COUNT><MEAN method="simple">-0.13656</MEAN><ERROR method="simple">0.00124</ERROR></BINNED>
      <BINNED size="16"><COUNT>3951</COUNT><MEAN method="simple">-0.13656</MEAN><ERROR method="simple">0.00132</ERROR></BINNED>
      <BINNED size="32"><COUNT>1975</COUNT><MEAN method="simple">-0.136543</MEAN><ERROR method="simple">0.00136</ERROR></BINNED>
      <BINNED size="64"><COUNT>987</COUNT><MEAN method="simple">-0.13651</MEAN><ERROR method="simple">0.00138</ERROR></BINNED>
      <BINNED size="128"><COUNT>493</COUNT><MEAN method="simple">-0.136481</MEAN><ERROR method="simple">0.00136</ERROR></BINNED>
      <BINNED size="256"><COUNT>246</COUNT><MEAN method="simple">-0.13643</MEAN><ERROR method="simple">0.00139</ERROR></BINNED>
    </SCALAR_AVERAGE>
    <SCALAR_AVERAGE name="Magnetization">
      <COUNT>63223</COUNT>
      <MEAN method="simple">-0.00176</MEAN>
      <ERROR converged="yes" method="binning">0.0045</ERROR>
      <VARIANCE method="simple">1.09</VARIANCE>
      <AUTOCORR method="binning">0.0861</AUTOCORR>
      <BINNED size="1"><COUNT>63223</COUNT><MEAN method="simple">-0.00176</MEAN><ERROR method="simple">0.00416</ERROR></BINNED>
      <BINNED size="2"><COUNT>31611</COUNT><MEAN method="simple">-0.00176</MEAN><ERROR method="simple">0.0042</ERROR></BINNED>
      <BINNED size="4"><COUNT>15805</COUNT><MEAN method="simple">-0.00177</MEAN><ERROR method="simple">0.00423</ERROR></BINNED>
      <BINNED size="8"><COUNT>7902</COUNT><MEAN method="simple">-0.00179</MEAN><ERROR method="simple">0.00426</ERROR></BINNED>
      <BINNED size="16"><COUNT>3951</COUNT><MEAN method="simple">-0.00179</MEAN><ERROR method="simple">0.00428</ERROR></BINNED>
      <BINNED size="32"><COUNT>1975</COUNT><MEAN method="simple">-0.00184</MEAN><ERROR method="simple">0.00425</ERROR></BINNED>
      <BINNED size="64"><COUNT>987</COUNT><MEAN method="simple">-0.00171</MEAN><ERROR method="simple">0.0043</ERROR></BINNED>
      <BINNED size="128"><COUNT>493</COUNT><MEAN method="simple">-0.00154</MEAN><ERROR method="simple">0.0044</ERROR></BINNED>
      <BINNED size="256"><COUNT>246</COUNT><MEAN method="simple">-0.00165</MEAN><ERROR method="simple">0.0045</ERROR></BINNED>
    </SCALAR_AVERAGE>
    <SCALAR_AVERAGE name="Magnetization Density">
      <COUNT>63223</COUNT>
      <MEAN method="simple">-0.000219</MEAN>
      <ERROR converged="yes" method="binning">0.000563</ERROR>
      <VARIANCE method="simple">0.0171</VARIANCE>
      <AUTOCORR method="binning">0.0861</AUTOCORR>
      <BINNED size="1"><COUNT>63223</COUNT><MEAN method="simple">-0.000219</MEAN><ERROR method="simple">0.00052</ERROR></BINNED>
      <BINNED size="2"><COUNT>31611</COUNT><MEAN method="simple">-0.000219</MEAN><ERROR method="simple">0.000525</ERROR></BINNED>
      <BINNED size="4"><COUNT>15805</COUNT><MEAN method="simple">-0.000221</MEAN><ERROR method="simple">0.000528</ERROR></BINNED>
      <BINNED size="8"><COUNT>7902</COUNT><MEAN method="simple">-0.000223</MEAN><ERROR method="simple">0.000533</ERROR></BINNED>
      <BINNED size="16"><COUNT>3951</COUNT><MEAN method="simple">-0.000223</MEAN><ERROR method="simple">0.000535</ERROR></BINNED>
      <BINNED size="32"><COUNT>1975</COUNT><MEAN method="simple">-0.000229</MEAN><ERROR method="simple">0.000531</ERROR></BINNED>
      <BINNED size="64"><COUNT>987</COUNT><MEAN method="simple">-0.000214</MEAN><ERROR method="simple">0.000537</ERROR></BINNED>
      <BINNED size="128"><COUNT>493</COUNT><MEAN method="simple">-0.000192</MEAN><ERROR method="simple">0.00055</ERROR></BINNED>
      <BINNED size="256"><COUNT>246</COUNT><MEAN method="simple">-0.000206</MEAN><ERROR method="simple">0.000563</ERROR></BINNED>
    </SCALAR_AVERAGE>
    <SCALAR_AVERAGE name="Magnetization Density^2">
      <COUNT>63223</COUNT>
      <MEAN method="simple">0.0170851</MEAN>
      <ERROR converged="yes" method="binning">9.69e-05</ERROR>
      <VARIANCE method="simple">0.00059</VARIANCE>
      <AUTOCORR method="binning">0.00313</AUTOCORR>
      <BINNED size="1"><COUNT>63223</COUNT><MEAN method="simple">0.0170851</MEAN><ERROR method="simple">9.66e-05</ERROR></BINNED>
      <BINNED size="2"><COUNT>31611</COUNT><MEAN method="simple">0.0170854</MEAN><ERROR method="simple">9.96e-05</ERROR></BINNED>
      <BINNED size="4"><COUNT>15805</COUNT><MEAN method="simple">0.0170857</MEAN><ERROR method="simple">0.000102</ERROR></BINNED>
      <BINNED size="8"><COUNT>7902</COUNT><MEAN method="simple">0.017086</MEAN><ERROR method="simple">0.000104</ERROR></BINNED>
      <BINNED size="16"><COUNT>3951</COUNT><MEAN method="simple">0.017086</MEAN><ERROR method="simple">0.000105</ERROR></BINNED>
      <BINNED size="32"><COUNT>1975</COUNT><MEAN method="simple">0.0170876</MEAN><ERROR method="simple">0.000103</ERROR></BINNED>
      <BINNED size="64"><COUNT>987</COUNT><MEAN method="simple">0.0170918</MEAN><ERROR method="simple">0.000104</ERROR></BINNED>
      <BINNED size="128"><COUNT>493</COUNT><MEAN method="simple">0.0170965</MEAN><ERROR method="simple">0.000104</ERROR></BINNED>
      <BINNED size="256"><COUNT>246</COUNT><MEAN method="simple">0.0171018</MEAN><ERROR method="simple">9.69e-05</ERROR></BINNED>
    </SCALAR_AVERAGE>
    <SCALAR_AVERAGE name="Magnetization Density^4">
      <COUNT>63223</COUNT>
      <MEAN method="simple">0.00088173</MEAN>
      <ERROR converged="yes" method="binning">1.18e-05</ERROR>
      <VARIANCE method="simple">8.3e-06</VARIANCE>
      <AUTOCORR method="binning">0.0319</AUTOCORR>
      <BINNED size="1"><COUNT>63223</COUNT><MEAN method="simple">0.00088173</MEAN><ERROR method="simple">1.15e-05</ERROR></BINNED>
      <BINNED size="2"><COUNT>31611</COUNT><MEAN method="simple">0.00088175</MEAN><ERROR method="simple">1.16e-05</ERROR></BINNED>
      <BINNED size="4"><COUNT>15805</COUNT><MEAN method="simple">0.00088177</MEAN><ERROR method="simple">1.18e-05</ERROR></BINNED>
      <BINNED size="8"><COUNT>7902</COUNT><MEAN method="simple">0.00088182</MEAN><ERROR method="simple">1.2e-05</ERROR></BINNED>
      <BINNED size="16"><COUNT>3951</COUNT><MEAN method="simple">0.00088182</MEAN><ERROR method="simple">1.2e-05</ERROR></BINNED>
      <BINNED size="32"><COUNT>1975</COUNT><MEAN method="simple">0.000882</MEAN><ERROR method="simple">1.18e-05</ERROR></BINNED>
      <BINNED size="64"><COUNT>987</COUNT><MEAN method="simple">0.00088233</MEAN><ERROR method="simple">1.2e-05</ERROR></BINNED>
      <BINNED size="128"><COUNT>493</COUNT><MEAN method="simple">0.00088275</MEAN><ERROR method="simple">1.21e-05</ERROR></BINNED>
      <BINNED size="256"><COUNT>246</COUNT><MEAN method="simple">0.00088352</MEAN><ERROR method="simple">1.18e-05</ERROR></BINNED>
    </SCALAR_AVERAGE>
    <SCALAR_AVERAGE name="Magnetization^2">
      <COUNT>63223</COUNT>
      <MEAN method="simple">1.09345</MEAN>
      <ERROR converged="yes" method="binning">0.0062</ERROR>
      <VARIANCE method="simple">2.42</VARIANCE>
      <AUTOCORR method="binning">0.00313</AUTOCORR>
      <BINNED size="1"><COUNT>63223</COUNT><MEAN method="simple">1.09345</MEAN><ERROR method="simple">0.00618</ERROR></BINNED>
      <BINNED size="2"><COUNT>31611</COUNT><MEAN method="simple">1.09346</MEAN><ERROR method="simple">0.00637</ERROR></BINNED>
      <BINNED size="4"><COUNT>15805</COUNT><MEAN method="simple">1.09348</MEAN><ERROR method="simple">0.00654</ERROR></BINNED>
      <BINNED size="8"><COUNT>7902</COUNT><MEAN method="simple">1.0935</MEAN><ERROR method="simple">0.00664</ERROR></BINNED>
      <BINNED size="16"><COUNT>3951</COUNT><MEAN method="simple">1.0935</MEAN><ERROR method="simple">0.00672</ERROR></BINNED>
      <BINNED size="32"><COUNT>1975</COUNT><MEAN method="simple">1.09361</MEAN><ERROR method="simple">0.00659</ERROR></BINNED>
      <BINNED size="64"><COUNT>987</COUNT><MEAN method="simple">1.09388</MEAN><ERROR method="simple">0.00666</ERROR></BINNED>
      <BINNED size="128"><COUNT>493</COUNT><MEAN method="simple">1.09418</MEAN><ERROR method="simple">0.00663</ERROR></BINNED>
      <BINNED size="256"><COUNT>246</COUNT><MEAN method="simple">1.09451</MEAN><ERROR method="simple">0.0062</ERROR></BINNED>
    </SCALAR_AVERAGE>
    <SCALAR_AVERAGE name="Magnetization^4">
      <COUNT>63223</COUNT>
      <MEAN method="simple">3.6116</MEAN>
      <ERROR converged="yes" method="binning">0.0484</ERROR>
      <VARIANCE method="simple">139</VARIANCE>
      <AUTOCORR method="binning">0.0319</AUTOCORR>
      <BINNED size="1"><COUNT>63223</COUNT><MEAN method="simple">3.6116</MEAN><ERROR method="simple">0.0469</ERROR></BINNED>
      <BINNED size="2"><COUNT>31611</COUNT><MEAN method="simple">3.6116</MEAN><ERROR method="simple">0.0476</ERROR></BINNED>
      <BINNED size="4"><COUNT>15805</COUNT><MEAN method="simple">3.6117</MEAN><ERROR method="simple">0.0483</ERROR></BINNED>
      <BINNED size="8"><COUNT>7902</COUNT><MEAN method="simple">3.6119</MEAN><ERROR method="simple">0.0491</ERROR></BINNED>
      <BINNED size="16"><COUNT>3951</COUNT><MEAN method="simple">3.6119</MEAN><ERROR method="simple">0.0493</ERROR></BINNED>
      <BINNED size="32"><COUNT>1975</COUNT><MEAN method="simple">3.6127</MEAN><ERROR method="simple">0.0484</ERROR></BINNED>
      <BINNED size="64"><COUNT>987</COUNT><MEAN method="simple">3.614</MEAN><ERROR method="simple">0.0492</ERROR></BINNED>
      <BINNED size="128"><COUNT>493</COUNT><MEAN method="simple">3.6157</MEAN><ERROR method="simple">0.0494</ERROR></BINNED>
      <BINNED size="256"><COUNT>246</COUNT><MEAN method="simple">3.6189</MEAN><ERROR method="simple">0.0484</ERROR></BINNED>
    </SCALAR_AVERAGE>
    <SCALAR_AVERAGE name="Staggered Magnetization">
      <COUNT>63223</COUNT>
      <MEAN method="simple">0.01128</MEAN>
      <ERROR converged="yes" method="binning">0.00822</ERROR>
      <VARIANCE method="simple">3.4</VARIANCE>
      <AUTOCORR method="binning">0.128</AUTOCORR>
      <BINNED size="1"><COUNT>63223</COUNT><MEAN method="simple">0.01128</MEAN><ERROR method="simple">0.00733</ERROR></BINNED>
      <BINNED size="2"><COUNT>31611</COUNT><MEAN method="simple">0.01131</MEAN><ERROR method="simple">0.00772</ERROR></BINNED>
      <BINNED size="4"><COUNT>15805</COUNT><MEAN method="simple">0.01129</MEAN><ERROR method="simple">0.00797</ERROR></BINNED>
      <BINNED size="8"><COUNT>7902</COUNT><MEAN method="simple">0.01118</MEAN><ERROR method="simple">0.00813</ERROR></BINNED>
      <BINNED size="16"><COUNT>3951</COUNT><MEAN method="simple">0.01118</MEAN><ERROR method="simple">0.00816</ERROR></BINNED>
      <BINNED size="32"><COUNT>1975</COUNT><MEAN method="simple">0.01111</MEAN><ERROR method="simple">0.00826</ERROR></BINNED>
      <BINNED size="64"><COUNT>987</COUNT><MEAN method="simple">0.01121</MEAN><ERROR method="simple">0.00839</ERROR></BINNED>
      <BINNED size="128"><COUNT>493</COUNT><MEAN method="simple">0.0112</MEAN><ERROR method="simple">0.00814</ERROR></BINNED>
      <BINNED size="256"><COUNT>246</COUNT><MEAN method="simple">0.01127</MEAN><ERROR method="simple">0.00822</ERROR></BINNED>
    </SCALAR_AVERAGE>
    <SCALAR_AVERAGE name="Staggered Magnetization Density">
      <COUNT>63223</COUNT>
      <MEAN method="simple">0.00141</MEAN>
      <ERROR converged="yes" method="binning">0.00103</ERROR>
      <VARIANCE method="simple">0.0531</VARIANCE>
      <AUTOCORR method="binning">0.128</AUTOCORR>
      <BINNED size="1"><COUNT>63223</COUNT><MEAN method="simple">0.00141</MEAN><ERROR method="simple">0.000917</ERROR></BINNED>
      <BINNED size="2"><COUNT>31611</COUNT><MEAN method="simple">0.001414</MEAN><ERROR method="simple">0.000966</ERROR></BINNED>
      <BINNED size="4"><COUNT>15805</COUNT><MEAN method="simple">0.001412</MEAN><ERROR method="simple">0.000996</ERROR></BINNED>
      <BINNED size="8"><COUNT>7902</COUNT><MEAN method="simple">0.001398</MEAN><ERROR method="simple">0.00102</ERROR></BINNED>
      <BINNED size="16"><COUNT>3951</COUNT><MEAN method="simple">0.001398</MEAN><ERROR method="simple">0.00102</ERROR></BINNED>
      <BINNED size="32"><COUNT>1975</COUNT><MEAN method="simple">0.001388</MEAN><ERROR method="simple">0.00103</ERROR></BINNED>
      <BINNED size="64"><COUNT>987</COUNT><MEAN method="simple">0.001401</MEAN><ERROR method="simple">0.00105</ERROR></BINNED>
      <BINNED size="128"><COUNT>493</COUNT><MEAN method="simple">0.0014</MEAN><ERROR method="simple">0.00102</ERROR></BINNED>
      <BINNED size="256"><COUNT>246</COUNT><MEAN method="simple">0.001409</MEAN><ERROR method="simple">0.00103</ERROR></BINNED>
    </SCALAR_AVERAGE>
    <SCALAR_AVERAGE name="Staggered Magnetization Density^2">
      <COUNT>63223</COUNT>
      <MEAN method="simple">0.0531351</MEAN>
      <ERROR converged="yes" method="binning">0.000282</ERROR>
      <VARIANCE method="simple">0.00409</VARIANCE>
      <AUTOCORR method="binning">0.117</AUTOCORR>
      <BINNED size="1"><COUNT>63223</COUNT><MEAN method="simple">0.0531351</MEAN><ERROR method="simple">0.000254</ERROR></BINNED>
      <BINNED size="2"><COUNT>31611</COUNT><MEAN method="simple">0.0531349</MEAN><ERROR method="simple">0.000266</ERROR></BINNED>
      <BINNED size="4"><COUNT>15805</COUNT><MEAN method="simple">0.0531364</MEAN><ERROR method="simple">0.000274</ERROR></BINNED>
      <BINNED size="8"><COUNT>7902</COUNT><MEAN method="simple">0.053135</MEAN><ERROR method="simple">0.000277</ERROR></BINNED>
      <BINNED size="16"><COUNT>3951</COUNT><MEAN method="simple">0.053135</MEAN><ERROR method="simple">0.000279</ERROR></BINNED>
      <BINNED size="32"><COUNT>1975</COUNT><MEAN method="simple">0.053124</MEAN><ERROR method="simple">0.000281</ERROR></BINNED>
      <BINNED size="64"><COUNT>987</COUNT><MEAN method="simple">0.0531207</MEAN><ERROR method="simple">0.00028</ERROR></BINNED>
      <BINNED size="128"><COUNT>493</COUNT><MEAN method="simple">0.0531204</MEAN><ERROR method="simple">0.00027</ERROR></BINNED>
      <BINNED size="256"><COUNT>246</COUNT><MEAN method="simple">0.0531204</MEAN><ERROR method="simple">0.000282</ERROR></BINNED>
    </SCALAR_AVERAGE>
    <SCALAR_AVERAGE name="Staggered Magnetization Density^4">
      <COUNT>63223</COUNT>
      <MEAN method="simple">0.00691055</MEAN>
      <ERROR converged="yes" method="binning">6.39e-05</ERROR>
      <VARIANCE method="simple">0.000207</VARIANCE>
      <AUTOCORR method="binning">0.124</AUTOCORR>
      <BINNED size="1"><COUNT>63223</COUNT><MEAN method="simple">0.00691055</MEAN><ERROR method="simple">5.72e-05</ERROR></BINNED>
      <BINNED size="2"><COUNT>31611</COUNT><MEAN method="simple">0.0069106</MEAN><ERROR method="simple">5.97e-05</ERROR></BINNED>
      <BINNED size="4"><COUNT>15805</COUNT><MEAN method="simple">0.00691082</MEAN><ERROR method="simple">6.14e-05</ERROR></BINNED>
      <BINNED size="8"><COUNT>7902</COUNT><MEAN method="simple">0.00691062</MEAN><ERROR method="simple">6.21e-05</ERROR></BINNED>
      <BINNED size="16"><COUNT>3951</COUNT><MEAN method="simple">0.00691062</MEAN><ERROR method="simple">6.28e-05</ERROR></BINNED>
      <BINNED size="32"><COUNT>1975</COUNT><MEAN method="simple">0.00690838</MEAN><ERROR method="simple">6.28e-05</ERROR></BINNED>
      <BINNED size="64"><COUNT>987</COUNT><MEAN method="simple">0.0069083</MEAN><ERROR method="simple">6.22e-05</ERROR></BINNED>
      <BINNED size="128"><COUNT>493</COUNT><MEAN method="simple">0.00690944</MEAN><ERROR method="simple">6.13e-05</ERROR></BINNED>
      <BINNED size="256"><COUNT>246</COUNT><MEAN method="simple">0.00690882</MEAN><ERROR method="simple">6.39e-05</ERROR></BINNED>
    </SCALAR_AVERAGE>
    <SCALAR_AVERAGE name="Staggered Magnetization^2">
      <COUNT>63223</COUNT>
      <MEAN method="simple">3.40065</MEAN>
      <ERROR converged="yes" method="binning">0.0181</ERROR>
      <VARIANCE method="simple">16.7</VARIANCE>
      <AUTOCORR method="binning">0.117</AUTOCORR>
      <BINNED size="1"><COUNT>63223</COUNT><MEAN method="simple">3.40065</MEAN><ERROR method="simple">0.0163</ERROR></BINNED>
      <BINNED size="2"><COUNT>31611</COUNT><MEAN method="simple">3.40064</MEAN><ERROR method="simple">0.017</ERROR></BINNED>
      <BINNED size="4"><COUNT>15805</COUNT><MEAN method="simple">3.40073</MEAN><ERROR method="simple">0.0175</ERROR></BINNED>
      <BINNED size="8"><COUNT>7902</COUNT><MEAN method="simple">3.40064</MEAN><ERROR method="simple">0.0177</ERROR></BINNED>
      <BINNED size="16"><COUNT>3951</COUNT><MEAN method="simple">3.40064</MEAN><ERROR method="simple">0.0179</ERROR></BINNED>
      <BINNED size="32"><COUNT>1975</COUNT><MEAN method="simple">3.39994</MEAN><ERROR method="simple">0.018</ERROR></BINNED>
      <BINNED size="64"><COUNT>987</COUNT><MEAN method="simple">3.39973</MEAN><ERROR method="simple">0.0179</ERROR></BINNED>
      <BINNED size="128"><COUNT>493</COUNT><MEAN method="simple">3.39971</MEAN><ERROR method="simple">0.0173</ERROR></BINNED>
      <BINNED size="256"><COUNT>246</COUNT><MEAN method="simple">3.39971</MEAN><ERROR method="simple">0.0181</ERROR></BINNED>
    </SCALAR_AVERAGE>
    <SCALAR_AVERAGE name="Staggered Magnetization^4">
      <COUNT>63223</COUNT>
      <MEAN method="simple">28.3056</MEAN>
      <ERROR converged="yes" method="binning">0.262</ERROR>
      <VARIANCE method="simple">3.47e+03</VARIANCE>
      <AUTOCORR method="binning">0.124</AUTOCORR>
      <BINNED size="1"><COUNT>63223</COUNT><MEAN method="simple">28.3056</MEAN><ERROR method="simple">0.234</ERROR></BINNED>
      <BINNED size="2"><COUNT>31611</COUNT><MEAN method="simple">28.3058</MEAN><ERROR method="simple">0.245</ERROR></BINNED>
      <BINNED size="4"><COUNT>15805</COUNT><MEAN method="simple">28.3067</MEAN><ERROR method="simple">0.251</ERROR></BINNED>
      <BINNED size="8"><COUNT>7902</COUNT><MEAN method="simple">28.3059</MEAN><ERROR method="simple">0.254</ERROR></BINNED>
      <BINNED size="16"><COUNT>3951</COUNT><MEAN method="simple">28.3059</MEAN><ERROR method="simple">0.257</ERROR></BINNED>
      <BINNED size="32"><COUNT>1975</COUNT><MEAN method="simple">28.2967</MEAN><ERROR method="simple">0.257</ERROR></BINNED>
      <BINNED size="64"><COUNT>987</COUNT><MEAN method="simple">28.2964</MEAN><ERROR method="simple">0.255</ERROR></BINNED>
      <BINNED size="128"><COUNT>493</COUNT><MEAN method="simple">28.3011</MEAN><ERROR method="simple">0.251</ERROR></BINNED>
      <BINNED size="256"><COUNT>246</COUNT><MEAN method="simple">28.2985</MEAN><ERROR method="simple">0.262</ERROR></BINNED>
    </SCALAR_AVERAGE>
    <SCALAR_AVERAGE name="Stiffness">
      <COUNT>63223</COUNT>
      <MEAN method="simple">0.0001424</MEAN>
      <ERROR converged="yes" method="binning">7.58e-05</ERROR>
      <VARIANCE method="simple">0.000142</VARIANCE>
      <AUTOCORR method="binning">0.775</AUTOCORR>
      <BINNED size="1"><COUNT>63223</COUNT><MEAN method="simple">0.0001424</MEAN><ERROR method="simple">4.74e-05</ERROR></BINNED>
      <BINNED size="2"><COUNT>31611</COUNT><MEAN method="simple">0.0001424</MEAN><ERROR method="simple">5.7e-05</ERROR></BINNED>
      <BINNED size="4"><COUNT>15805</COUNT><MEAN method="simple">0.0001424</MEAN><ERROR method="simple">6.52e-05</ERROR></BINNED>
      <BINNED size="8"><COUNT>7902</COUNT><MEAN method="simple">0.0001424</MEAN><ERROR method="simple">6.52e-05</ERROR></BINNED>
      <BINNED size="16"><COUNT>3951</COUNT><MEAN method="simple">0.0001424</MEAN><ERROR method="simple">6.52e-05</ERROR></BINNED>
      <BINNED size="32"><COUNT>1975</COUNT><MEAN method="simple">0.0001424</MEAN><ERROR method="simple">7.58e-05</ERROR></BINNED>
      <BINNED size="64"><COUNT>987</COUNT><MEAN method="simple">0.0001425</MEAN><ERROR method="simple">7.58e-05</ERROR></BINNED>
      <BINNED size="128"><COUNT>493</COUNT><MEAN method="simple">0.0001426</MEAN><ERROR method="simple">7.58e-05</ERROR></BINNED>
      <BINNED size="256"><COUNT>246</COUNT><MEAN method="simple">0.0001429</MEAN><ERROR method="simple">7.58e-05</ERROR></BINNED>
    </SCALAR_AVERAGE>
    <SCALAR_AVERAGE name="Susceptibility">
      <COUNT>63223</COUNT>
      <MEAN method="simple">0.136681</MEAN>
      <ERROR converged="yes" method="binning">0.000775</ERROR>
      <VARIANCE method="simple">0.0377</VARIANCE>
      <AUTOCORR method="binning">0.00313</AUTOCORR>
      <BINNED size="1"><COUNT>63223</COUNT><MEAN method="simple">0.136681</MEAN><ERROR method="simple">0.000773</ERROR></BINNED>
      <BINNED size="2"><COUNT>31611</COUNT><MEAN method="simple">0.136683</MEAN><ERROR method="simple">0.000797</ERROR></BINNED>
      <BINNED size="4"><COUNT>15805</COUNT><MEAN method="simple">0.136685</MEAN><ERROR method="simple">0.000818</ERROR></BINNED>
      <BINNED size="8"><COUNT>7902</COUNT><MEAN method="simple">0.136688</MEAN><ERROR method="simple">0.000831</ERROR></BINNED>
      <BINNED size="16"><COUNT>3951</COUNT><MEAN method="simple">0.136688</MEAN><ERROR method="simple">0.000841</ERROR></BINNED>
      <BINNED size="32"><COUNT>1975</COUNT><MEAN method="simple">0.136701</MEAN><ERROR method="simple">0.000824</ERROR></BINNED>
      <BINNED size="64"><COUNT>987</COUNT><MEAN method="simple">0.136735</MEAN><ERROR method="simple">0.000833</ERROR></BINNED>
      <BINNED size="128"><COUNT>493</COUNT><MEAN method="simple">0.136772</MEAN><ERROR method="simple">0.000829</ERROR></BINNED>
      <BINNED size="256"><COUNT>246</COUNT><MEAN method="simple">0.136814</MEAN><ERROR method="simple">0.000775</ERROR></BINNED>
    </SCALAR_AVERAGE>
    <SCALAR_AVERAGE name="n">
      <COUNT>63223</COUNT>
      <MEAN method="simple">3.63463</MEAN>
      <ERROR converged="yes" method="binning">0.0162</ERROR>
      <VARIANCE method="simple">5.17</VARIANCE>
      <AUTOCORR method="binning">1.11</AUTOCORR>
      <BINNED size="1"><COUNT>63223</COUNT><MEAN method="simple">3.63463</MEAN><ERROR method="simple">0.00904</ERROR></BINNED>
      <BINNED size="2"><COUNT>31611</COUNT><MEAN method="simple">3.63465</MEAN><ERROR method="simple">0.011</ERROR></BINNED>
      <BINNED size="4"><COUNT>15805</COUNT><MEAN method="simple">3.63472</MEAN><ERROR method="simple">0.013</ERROR></BINNED>
      <BINNED size="8"><COUNT>7902</COUNT><MEAN method="simple">3.63473</MEAN><ERROR method="simple">0.0145</ERROR></BINNED>
      <BINNED size="16"><COUNT>3951</COUNT><MEAN method="simple">3.63473</MEAN><ERROR method="simple">0.0154</ERROR></BINNED>
      <BINNED size="32"><COUNT>1975</COUNT><MEAN method="simple">3.63453</MEAN><ERROR method="simple">0.0159</ERROR></BINNED>
      <BINNED size="64"><COUNT>987</COUNT><MEAN method="simple">3.63413</MEAN><ERROR method="simple">0.016</ERROR></BINNED>
      <BINNED size="128"><COUNT>493</COUNT><MEAN method="simple">3.63384</MEAN><ERROR method="simple">0.016</ERROR></BINNED>
      <BINNED size="256"><COUNT>246</COUNT><MEAN method="simple">3.63305</MEAN><ERROR method="simple">0.0162</ERROR></BINNED>
    </SCALAR_AVERAGE>
    <SCALAR_AVERAGE name="n^2">
      <COUNT>63223</COUNT>
      <MEAN method="simple">18.3799</MEAN>
      <ERROR converged="yes" method="binning">0.148</ERROR>
      <VARIANCE method="simple">450</VARIANCE>
      <AUTOCORR method="binning">1.04</AUTOCORR>
      <BINNED size="1"><COUNT>63223</COUNT><MEAN method="simple">18.3799</MEAN><ERROR method="simple">0.0844</ERROR></BINNED>
      <BINNED size="2"><COUNT>31611</COUNT><MEAN method="simple">18.3802</MEAN><ERROR method="simple">0.102</ERROR></BINNED>
      <BINNED size="4"><COUNT>15805</COUNT><MEAN method="simple">18.3806</MEAN><ERROR method="simple">0.119</ERROR></BINNED>
      <BINNED size="8"><COUNT>7902</COUNT><MEAN method="simple">18.3809</MEAN><ERROR method="simple">0.133</ERROR></BINNED>
      <BINNED size="16"><COUNT>3951</COUNT><MEAN method="simple">18.3809</MEAN><ERROR method="simple">0.141</ERROR></BINNED>
      <BINNED size="32"><COUNT>1975</COUNT><MEAN method="simple">18.3795</MEAN><ERROR method="simple">0.145</ERROR></BINNED>
      <BINNED size="64"><COUNT>987</COUNT><MEAN method="simple">18.3769</MEAN><ERROR method="simple">0.148</ERROR></BINNED>
      <BINNED size="128"><COUNT>493</COUNT><MEAN method="simple">18.3762</MEAN><ERROR method="simple">0.148</ERROR></BINNED>
      <BINNED size="256"><COUNT>246</COUNT><MEAN method="simple">18.3696</MEAN><ERROR method="simple">0.148</ERROR></BINNED>
    </SCALAR_AVERAGE>
    <SCALAR_AVERAGE name="n^3">
      <COUNT>63223</COUNT>
      <MEAN method="simple">112.13</MEAN>
      <ERROR converged="yes" method="binning">1.32</ERROR>
      <VARIANCE method="simple">4.13e+04</VARIANCE>
      <AUTOCORR method="binning">0.841</AUTOCORR>
      <BINNED size="1"><COUNT>63223</COUNT><MEAN method="simple">112.131</MEAN><ERROR method="simple">0.808</ERROR></BINNED>
      <BINNED size="2"><COUNT>31611</COUNT><MEAN method="simple">112.133</MEAN><ERROR method="simple">0.952</ERROR></BINNED>
      <BINNED size="4"><COUNT>15805</COUNT><MEAN method="simple">112.136</MEAN><ERROR method="simple">1.1</ERROR></BINNED>
      <BINNED size="8"><COUNT>7902</COUNT><MEAN method="simple">112.14</MEAN><ERROR method="simple">1.22</ERROR></BINNED>
      <BINNED size="16"><COUNT>3951</COUNT><MEAN method="simple">112.14</MEAN><ERROR method="simple">1.28</ERROR></BINNED>
      <BINNED size="32"><COUNT>1975</COUNT><MEAN method="simple">112.13</MEAN><ERROR method="simple">1.31</ERROR></BINNED>
      <BINNED size="64"><COUNT>987</COUNT><MEAN method="simple">112.12</MEAN><ERROR method="simple">1.35</ERROR></BINNED>
      <BINNED size="128"><COUNT>493</COUNT><MEAN method="simple">112.13</MEAN><ERROR method="simple">1.35</ERROR></BINNED>
      <BINNED size="256"><COUNT>246</COUNT><MEAN method="simple">112.07</MEAN><ERROR method="simple">1.32</ERROR></BINNED>
    </SCALAR_AVERAGE>
    <SCALAR_AVERAGE name="|Magnetization Density|">
      <COUNT>63223</COUNT>
      <MEAN method="simple">0.0956278</MEAN>
      <ERROR converged="yes" method="binning">0.00035</ERROR>
      <VARIANCE method="simple">0.00794</VARIANCE>
      <AUTOCORR method="binning">-0.0116</AUTOCORR>
      <BINNED size="1"><COUNT>63223</COUNT><MEAN method="simple">0.0956278</MEAN><ERROR method="simple">0.000354</ERROR></BINNED>
      <BINNED size="2"><COUNT>31611</COUNT><MEAN method="simple">0.0956293</MEAN><ERROR method="simple">0.000366</ERROR></BINNED>
      <BINNED size="4"><COUNT>15805</COUNT><MEAN method="simple">0.0956303</MEAN><ERROR method="simple">0.000376</ERROR></BINNED>
      <BINNED size="8"><COUNT>7902</COUNT><MEAN method="simple">0.0956305</MEAN><ERROR method="simple">0.00038</ERROR></BINNED>
      <BINNED size="16"><COUNT>3951</COUNT><MEAN method="simple">0.0956305</MEAN><ERROR method="simple">0.000385</ERROR></BINNED>
      <BINNED size="32"><COUNT>1975</COUNT><MEAN method="simple">0.0956329</MEAN><ERROR method="simple">0.00038</ERROR></BINNED>
      <BINNED size="64"><COUNT>987</COUNT><MEAN method="simple">0.0956497</MEAN><ERROR method="simple">0.000382</ERROR></BINNED>
      <BINNED size="128"><COUNT>493</COUNT><MEAN method="simple">0.0956695</MEAN><ERROR method="simple">0.000374</ERROR></BINNED>
      <BINNED size="256"><COUNT>246</COUNT><MEAN method="simple">0.0956753</MEAN><ERROR method="simple">0.00035</ERROR></BINNED>
    </SCALAR_AVERAGE>
    <SCALAR_AVERAGE name="|Magnetization|">
      <COUNT>63223</COUNT>
      <MEAN method="simple">0.765022</MEAN>
      <ERROR converged="yes" method="binning">0.0028</ERROR>
      <VARIANCE method="simple">0.508</VARIANCE>
      <AUTOCORR method="binning">-0.0116</AUTOCORR>
      <BINNED size="1"><COUNT>63223</COUNT><MEAN method="simple">0.765022</MEAN><ERROR method="simple">0.00284</ERROR></BINNED>
      <BINNED size="2"><COUNT>31611</COUNT><MEAN method="simple">0.765034</MEAN><ERROR method="simple">0.00293</ERROR></BINNED>
      <BINNED size="4"><COUNT>15805</COUNT><MEAN method="simple">0.765043</MEAN><ERROR method="simple">0.00301</ERROR></BINNED>
      <BINNED size="8"><COUNT>7902</COUNT><MEAN method="simple">0.765044</MEAN><ERROR method="simple">0.00304</ERROR></BINNED>
      <BINNED size="16"><COUNT>3951</COUNT><MEAN method="simple">0.765044</MEAN><ERROR method="simple">0.00308</ERROR></BINNED>
      <BINNED size="32"><COUNT>1975</COUNT><MEAN method="simple">0.765063</MEAN><ERROR method="simple">0.00304</ERROR></BINNED>
      <BINNED size="64"><COUNT>987</COUNT><MEAN method="simple">0.765198</MEAN><ERROR method="simple">0.00305</ERROR></BINNED>
      <BINNED size="128"><COUNT>493</COUNT><MEAN method="simple">0.765356</MEAN><ERROR method="simple">0.00299</ERROR></BINNED>
      <BINNED size="256"><COUNT>246</COUNT><MEAN method="simple">0.765403</MEAN><ERROR method="simple">0.0028</ERROR></BINNED>
    </SCALAR_AVERAGE>
  </AVERAGES>
  <MCRUN>
    <EXECUTED phase="equilibrating">
      <FROM>2018-Apr-18 10:28:03</FROM>
      <TO>2018-Apr-18 10:28:03</TO>
      <MACHINE><NAME>alex-HP</NAME></MACHINE>
    </EXECUTED>
    <EXECUTED phase="running">
      <FROM>2018-Apr-18 10:28:03</FROM>
      <TO>2018-Apr-18 10:28:05</TO>
      <MACHINE><NAME>alex-HP</NAME></MACHINE>
    </EXECUTED>
    <CHECKPOINT format="osiris" file="Heiz_chain_dirloop.task1.out.run1"/>
    <CHECKPOINT format="hdf5" file="Heiz_chain_dirloop.task1.out.run1.h5"/>
  </MCRUN>
</SIMULATION>
